cute_deltas/__init__.py
cute_deltas/_nbdev.py
cute_deltas/core.py
cute_deltas-0.0.1.dist-info/LICENSE
cute_deltas-0.0.1.dist-info/METADATA
cute_deltas-0.0.1.dist-info/WHEEL
cute_deltas-0.0.1.dist-info/entry_points.txt
cute_deltas-0.0.1.dist-info/top_level.txt
cute_deltas-0.0.1.dist-info/RECORD
