Metadata-Version: 2.1
Name: cute-deltas
Version: 0.0.1
Summary: A cute little python module for finding the deltas between different things.
Home-page: https://github.com/ncoop57/cute_deltas/tree/main/
Author: Nathan Cooper
Author-email: nathanallencooper@gmail.com
License: Apache Software License 2.0
Keywords: delta difference diff python cute
Platform: UNKNOWN
Classifier: Development Status :: 3 - Alpha
Classifier: Intended Audience :: Developers
Classifier: License :: OSI Approved :: Apache Software License
Classifier: Natural Language :: English
Classifier: Programming Language :: Python :: 3.6
Classifier: Programming Language :: Python :: 3.7
Classifier: Programming Language :: Python :: 3.8
Requires-Python: >=3.6
